{
  "title": "Shop - Gaushala USA",
  "navigation": [
    {
      "text": "Home",
      "href": "https://gaushalausa.org"
    },
    {
      "text": "2",
      "href": "https://gaushalausa.org/shop/page/2/"
    },
    {
      "text": "Next Page",
      "href": "https://gaushalausa.org/shop/page/2/"
    }
  ],
  "mainContent": {
    "hero": {
      "title": "Shop",
      "subtitle": ""
    },
    "sections": []
  },
  "images": [],
  "text": [
    {
      "type": "p",
      "content": "Your cart is currently empty!"
    },
    {
      "type": "h1",
      "content": "Shop"
    },
    {
      "type": "p",
      "content": "Showing 1–3 of 5 results"
    },
    {
      "type": "h3",
      "content": "A2 Ghee – 2lbs"
    },
    {
      "type": "h3",
      "content": "Cow Dung Cakes-2lb(Approx.)"
    },
    {
      "type": "h3",
      "content": "A2 Ghee – 6lbs"
    },
    {
      "type": "h1",
      "content": "Gaushala USA"
    },
    {
      "type": "p",
      "content": "Powered by WordPress with WooCommerce"
    }
  ]
}